Metadata-Version: 2.1
Name: D-algorithm
Version: 1.0.0
Summary: D-algorithm
Home-page: UNKNOWN
Author: EasonCyx
Author-email: chengyixuan130812@163.com
License: UNKNOWN
Platform: UNKNOWN
Classifier: Programming Language :: Python :: 3
Classifier: License :: OSI Approved :: MIT License
Classifier: Operating System :: OS Independent
